.gitignore
LICENSE
README.md
requirements.txt
setup.cfg
setup.py
pynida/__main__.py
pynida/backend.py
pynida/config.cfg
pynida/frames_preview.py
pynida/frontend.py
pynida/frontend.ui
pynida/launch.py
pynida/simple_functions.py
pynida/window_comparison.py
pynida.egg-info/PKG-INFO
pynida.egg-info/SOURCES.txt
pynida.egg-info/dependency_links.txt
pynida.egg-info/entry_points.txt
pynida.egg-info/requires.txt
pynida.egg-info/top_level.txt
pynida/classes/__init__.py
pynida/classes/line.py
pynida/classes/point.py
pynida/classes/points.py
tests/__init__.py
tests/test_oneshot_contours.py
tests/area_finder/__main__.py
tests/area_finder/src/__init__.py
tests/area_finder/src/circle.py
tests/area_finder/src/rectangle.py
tests/area_finder/src/square.py
tests/data/testframe.pkl